{"chunk_definitions":[{"row":14,"row_count":1,"visible":true,"expansion_state":0,"options":{"engine":"r","label":"setup","include":false},"document_id":"DC479752","chunk_id":"csetup_chunk","chunk_label":"setup"},{"row":29,"row_count":1,"visible":true,"expansion_state":0,"options":{"engine":"r","message":false,"eval":false,"label":"unnamed-chunk-400"},"document_id":"DC479752","chunk_id":"cxf6zmm3c7lkh","chunk_label":"unnamed-chunk-1"},{"row":165,"row_count":1,"visible":true,"expansion_state":0,"options":{"engine":"r","label":"unnamed-chunk-406"},"document_id":"DC479752","chunk_id":"ch1iotw8aq4n4","chunk_label":"unnamed-chunk-7"},{"row":217,"row_count":1,"visible":true,"expansion_state":0,"options":{"engine":"r","label":"unnamed-chunk-226"},"document_id":"DC479752","chunk_id":"com0u03n2i1r3","chunk_label":"unnamed-chunk-9"},{"row":338,"row_count":1,"visible":true,"expansion_state":0,"options":{"engine":"r","message":false,"label":"unnamed-chunk-399"},"document_id":"DC479752","chunk_id":"czhqsyot414hg","chunk_label":"unnamed-chunk-11"},{"row":353,"row_count":1,"visible":true,"expansion_state":0,"options":{"engine":"r","label":"unnamed-chunk-505"},"document_id":"DC479752","chunk_id":"c05li7w8zsbku","chunk_label":"unnamed-chunk-12"},{"row":366,"row_count":1,"visible":true,"expansion_state":0,"options":{"engine":"r","label":"unnamed-chunk-529"},"document_id":"DC479752","chunk_id":"cxedrjqv33n62","chunk_label":"unnamed-chunk-13"},{"row":401,"row_count":1,"visible":true,"expansion_state":0,"options":{"engine":"r","eval":false,"label":"unnamed-chunk-452"},"document_id":"DC479752","chunk_id":"cwm0jk9o06xro","chunk_label":"unnamed-chunk-14"}],"doc_write_time":1595606515}